Metadata-Version: 1.1
Name: websocket-client-py3
Version: 0.13.1
Summary: WebSocket client for python3. hybi13 is supported.
Home-page: https://github.com/liris/websocket-client
Author: liris
Author-email: liris.pp@gmail.com
License: LGPL
Keywords: websockets
Platform: UNKNOWN
Classifier: Development Status :: 3 - Alpha
Classifier: License :: OSI Approved :: GNU Library or Lesser General Public License (LGPL)
Classifier: Programming Language :: Python
Classifier: Operating System :: MacOS :: MacOS X
Classifier: Operating System :: POSIX
Classifier: Operating System :: Microsoft :: Windows
Classifier: Topic :: Internet
Classifier: Topic :: Software Development :: Libraries :: Python Modules
Classifier: Intended Audience :: Developers
